langchain_pipeshift/__init__.py
langchain_pipeshift/chat_models.py
langchain_pipeshift/llms.py
langchain_pipeshift/py.typed
langchain_pipeshift-0.1.1.dist-info/LICENSE
langchain_pipeshift-0.1.1.dist-info/METADATA
langchain_pipeshift-0.1.1.dist-info/WHEEL
langchain_pipeshift-0.1.1.dist-info/RECORD
