Metadata-Version: 2.3
Name: langchain-pipeshift
Version: 0.1.1
Summary: An integration package connecting Pipeshift and LangChain
Home-page: https://github.com/pipeshift-org/langchain-pipeshift
License: MIT
Author: Pipeshift
Requires-Python: >=3.9,<4.0
Classifier: License :: OSI Approved :: MIT License
Classifier: Programming Language :: Python :: 3
Classifier: Programming Language :: Python :: 3.9
Classifier: Programming Language :: Python :: 3.10
Classifier: Programming Language :: Python :: 3.11
Classifier: Programming Language :: Python :: 3.12
Classifier: Programming Language :: Python :: 3.13
Requires-Dist: aiohttp (>=3.9.5,<4.0.0)
Requires-Dist: importlib-metadata (>=8.5.0,<9.0.0)
Requires-Dist: langchain-community (>=0.3.14,<0.4.0)
Requires-Dist: langchain-core (>=0.3.15,<0.4.0)
Requires-Dist: langchain-openai (>=0.2.1,<0.3.0)
Requires-Dist: openai (>=1.51.0,<2.0.0)
Requires-Dist: requests (>=2.32.3,<3.0.0)
Project-URL: Repository, https://github.com/pipeshift-org/langchain-pipeshift
Project-URL: Release Notes, https://github.com/pipeshift-org/langchain-pipeshift/releases
Project-URL: Source Code, https://github.com/pipeshift-org/langchain-pipeshift
